secret_vault.py
secret_vault-1.1.dist-info/METADATA
secret_vault-1.1.dist-info/WHEEL
secret_vault-1.1.dist-info/entry_points.txt
secret_vault-1.1.dist-info/top_level.txt
secret_vault-1.1.dist-info/RECORD
