Metadata-Version: 2.1
Name: secret-vault
Version: 1.1
Summary: Python secret vault to encrypt and hide your files in a secure place.
Home-page: https://github.com/Manoj-Shan/secret_vault
Author: Maneesh Pradeep
Author-email: manojshan2002@gmail.com
License: MIT
Platform: UNKNOWN
Classifier: Topic :: Security
Classifier: Topic :: Security :: Cryptography
Classifier: License :: OSI Approved :: MIT License
Classifier: Operating System :: OS Independent
Classifier: Natural Language :: English
Classifier: Programming Language :: Python :: 3
Classifier: Programming Language :: Python
Classifier: Development Status :: 4 - Beta
Requires-Dist: cryptography
Requires-Dist: pyAesCrypt
